daplug_s3/__init__.py
daplug_s3/adapter.py
daplug_s3/types/__init__.py
daplug_s3/types/s3.py
daplug_s3-1.0.0b1.dist-info/licenses/LICENSE
tests/__init__.py
tests/integrations/__init__.py
tests/integrations/conftest.py
tests/integrations/test_adapter_integration.py
tests/integrations/mocks/__init__.py
tests/unit/__init__.py
tests/unit/conftest.py
tests/unit/test___init__.py
tests/unit/test_adapter.py
tests/unit/test_types.py
tests/unit/mocks/__init__.py
tests/unit/mocks/base_adapter.py
daplug_s3-1.0.0b1.dist-info/METADATA
daplug_s3-1.0.0b1.dist-info/WHEEL
daplug_s3-1.0.0b1.dist-info/top_level.txt
daplug_s3-1.0.0b1.dist-info/RECORD
