Metadata-Version: 2.4
Name: daplug-s3
Version: 1.0.0b1
Summary: Schema-aware DynamoDB adapter with prefixing, SNS hooks, and batching.
Home-page: https://github.com/dual/daplug-s3
Author: Paul Cruse III
Author-email: paulcruse3@gmail.com
License: Apache License 2.0
Project-URL: Homepage, https://github.com/dual/daplug-s3
Project-URL: Documentation, https://github.com/dual/daplug-s3#readme
Project-URL: Source Code, https://github.com/dual/daplug-s3
Project-URL: Bug Reports, https://github.com/dual/daplug-s3/issues
Project-URL: CI/CD, https://circleci.com/gh/dual/daplug-s3
Keywords: dynamodb,aws,ddb,normalizer,schema,sns,event-driven,database,adapter,python-library
Platform: any
Classifier: Development Status :: 3 - Alpha
Classifier: Environment :: Web Environment
Classifier: Environment :: Console
Classifier: Intended Audience :: Developers
Classifier: License :: OSI Approved :: Apache Software License
Classifier: Operating System :: OS Independent
Classifier: Topic :: Database :: Front-Ends
Classifier: Topic :: Software Development :: Libraries :: Python Modules
Classifier: Programming Language :: Python
Classifier: Programming Language :: Python :: 3
Classifier: Programming Language :: Python :: 3.9
Classifier: Programming Language :: Python :: 3.10
Classifier: Programming Language :: Python :: 3.11
Classifier: Programming Language :: Python :: 3 :: Only
Requires-Python: >=3.9
License-File: LICENSE
Requires-Dist: boto3==1.40.74; python_version >= "3.9"
Requires-Dist: botocore==1.40.74; python_version >= "3.9"
Requires-Dist: daplug-core==1.0.0b5; python_version >= "3.9"
Requires-Dist: jmespath==1.0.1; python_version >= "3.7"
Requires-Dist: jsonpickle==4.1.1; python_version >= "3.8"
Requires-Dist: jsonref==1.1.0; python_version >= "3.7"
Requires-Dist: python-dateutil==2.9.0.post0; python_version >= "2.7" and python_version not in "3.0, 3.1, 3.2"
Requires-Dist: pyyaml==6.0.3; python_version >= "3.8"
Requires-Dist: s3transfer==0.14.0; python_version >= "3.9"
Requires-Dist: simplejson==3.20.2; python_version >= "2.5" and python_version not in "3.0, 3.1, 3.2"
Requires-Dist: six==1.17.0; python_version >= "2.7" and python_version not in "3.0, 3.1, 3.2"
Requires-Dist: urllib3==1.26.20; python_version >= "2.7" and python_version not in "3.0, 3.1, 3.2, 3.3, 3.4, 3.5"
Dynamic: author
Dynamic: author-email
Dynamic: classifier
Dynamic: description
Dynamic: description-content-type
Dynamic: home-page
Dynamic: keywords
Dynamic: license
Dynamic: license-file
Dynamic: platform
Dynamic: project-url
Dynamic: requires-dist
Dynamic: requires-python
Dynamic: summary
